pynldas2/__init__.py
pynldas2/_utils.py
pynldas2/exceptions.py
pynldas2/print_versions.py
pynldas2/py.typed
pynldas2/pynldas2.py
pynldas2-0.19.3.dist-info/METADATA
pynldas2-0.19.3.dist-info/WHEEL
pynldas2-0.19.3.dist-info/licenses/AUTHORS.rst
pynldas2-0.19.3.dist-info/licenses/LICENSE
pynldas2-0.19.3.dist-info/RECORD
