Metadata-Version: 2.4
Name: pynldas2
Version: 0.19.3
Summary: Get NLDAS2 forcing data.
Project-URL: Changelog, https://docs.hyriver.io/changelogs/pynldas2.html
Project-URL: CI, https://github.com/hyriver/pynldas2/actions
Project-URL: Homepage, https://docs.hyriver.io/readme/pynldas2.html
Project-URL: Issues, https://github.com/hyriver/pynldas2/issues
Author-email: Taher Chegini <cheginit@gmail.com>
License: MIT
License-File: AUTHORS.rst
License-File: LICENSE
Classifier: Development Status :: 4 - Beta
Classifier: Intended Audience :: Science/Research
Classifier: License :: OSI Approved :: MIT License
Classifier: Operating System :: OS Independent
Classifier: Programming Language :: Python
Classifier: Programming Language :: Python :: 3 :: Only
Classifier: Programming Language :: Python :: 3.9
Classifier: Programming Language :: Python :: 3.10
Classifier: Programming Language :: Python :: 3.11
Classifier: Programming Language :: Python :: 3.12
Classifier: Programming Language :: Python :: 3.13
Classifier: Topic :: Scientific/Engineering
Classifier: Topic :: Scientific/Engineering :: Atmospheric Science
Classifier: Topic :: Scientific/Engineering :: GIS
Classifier: Topic :: Scientific/Engineering :: Hydrology
Classifier: Typing :: Typed
Requires-Python: >=3.9
Requires-Dist: netcdf4
Requires-Dist: numpy>=2
Requires-Dist: pandas>=1
Requires-Dist: pyproj>=3.0.1
Requires-Dist: rioxarray>=0.15
Requires-Dist: shapely>=2
Requires-Dist: tiny-retriever>=0.1.3
Requires-Dist: xarray>=2024.7
Provides-Extra: jit
Requires-Dist: numba>=0.60; extra == 'jit'
Provides-Extra: test
Requires-Dist: pytest-cov; extra == 'test'
Requires-Dist: pytest-sugar; extra == 'test'
